asyncmailer/__init__.py
asyncmailer/admin.py
asyncmailer/models.py
asyncmailer/tasks.py
asyncmailer/urls.py
asyncmailer/views.py
asyncmailer/management/__init__.py
asyncmailer/management/commands/__init__.py
asyncmailer/management/commands/hello.py
asyncmailer/migrations/0001_initial.py
asyncmailer/migrations/0002_auto_20160817_0106.py
asyncmailer/migrations/0003_auto_20160817_0107.py
asyncmailer/migrations/0004_auto_20180313_2103.py
asyncmailer/migrations/__init__.py
asyncmailer/static/asyncmailer/css/index.css
asyncmailer/templates/asyncmailer/index.html
asyncmailer/templates/email-templates/base.json
asyncmailer/templates/email-templates/email.html
asyncmailer/templates/email-templates/example.json
asyncmailer/templatetags/__init__.py
asyncmailer/templatetags/asyncmailer_tags.py
asyncmailer/tests/__init__.py
asyncmailer/tests/models_tests.py
asyncmailer/tests/settings.py
asyncmailer/tests/test_settings.py
asyncmailer/tests/urls.py
asyncmailer/tests/test_app/__init__.py
asyncmailer/tests/test_app/models.py
asyncmailer/tests/test_app/templates/400.html
asyncmailer/tests/test_app/templates/500.html
django_asyncmailer-1.6.1.dist-info/DESCRIPTION.rst
django_asyncmailer-1.6.1.dist-info/METADATA
django_asyncmailer-1.6.1.dist-info/RECORD
django_asyncmailer-1.6.1.dist-info/WHEEL
django_asyncmailer-1.6.1.dist-info/metadata.json
django_asyncmailer-1.6.1.dist-info/top_level.txt
