Metadata-Version: 2.0
Name: django-asyncmailer
Version: 1.6.1
Summary: Async email solution w/ multiple SMTP credentials, load-balancing and blacklist.
Requires-Dist: django
Requires-Dist: celery
Requires-Dist: django-compat
Requires-Dist: html2text
Requires-Dist: jsonfield
Requires-Dist: premailer
Provides-Extra: dev
Requires-Dist: flake8; extra == 'dev'
